[
  {
    "categoryId": 1,
    "brand": "Tesla",

    "name": "Tesla",
    "price": "1550000 ",
    "picture": "https://i.ibb.co/SrrmfvN/tesla.jpg",
    "location": "Dhaka mirpur- 1",
    "seller": "sayeed",
    "email": "sayeedh95@gmail.com",
    "verified": "true",
    "time": "3.00 pm",
    "sold": "available",
    "condition": "used",
    "used": "1 year",
    "originalPrice": 700000,
    "model": "Tesla 409",
    "authenticity": "original",
    "features": "Autopilot,Caraoke, Bioweapon defense mode ,Touchscreen, Streaming and video gaming,Web browser,Easter eggs, Air suspension",
    "describetion": "All Tesla models are equipped with a driver assistance system called Autopilot. "
  },
  {
    "categoryId": 1,
    "brand": "Tesla",
    "name": "Tesla",
    "price": "1550000 ",
    "picture": "https://i.ibb.co/SrrmfvN/tesla.jpg",
    "location": "Dhaka mirpur- 1",
    "seller": "sayeed",
    "email": "sayeedh95@gmail.com",
    "time": "3.00 pm",
    "sold": "available",
    "condition": "used",
    "used": "1 year",
    "originalPrice": 2700000,
    "model": "Tesla 409",
    "authenticity": "original",
    "features": "Autopilot,Caraoke, Bioweapon defense mode ,Touchscreen, Streaming and video gaming,Web browser,Easter eggs, Air suspension",
    "describetion": "All Tesla models are equipped with a driver assistance system called Autopilot. "
  },

  {
    "categoryId": 2,
    "brand": "Honda",

    "name": "Honda",
    "price": "1000000 ",
    "picture": "https://i.ibb.co/QYTV2Kx/civic.jpg",
    "location": "Dhaka mirpur- 10",
    "seller": "sayeed",
    "email": "sayeedh95@gmail.com",
    "time": "5.00 pm",
    "sold": "available",
    "condition": "used",
    "used": "1 year",
    "originalPrice": 1700000,
    "model": "Honda civic 409",
    "authenticity": "original",
    "Features": "Touchscreen, Streaming and video gaming,Web browser,Easter eggs, Air suspension",
    "describetion": " The Honda City is smartly styled with dignified stature and superior technological prowess. A wide, upper-grill in the front presents the signature Honda Solid Wing Face, and elevates the car to a position of prominence"
  },
  {
    "categoryId": 2,
    "brand": "Honda",

    "name": "Honda",
    "price": "1000000 ",
    "picture": "https://i.ibb.co/QYTV2Kx/civic.jpg",
    "location": "Dhaka mirpur- 10",
    "seller": "sayeed",
    "email": "sayeedh95@gmail.com",
    "time": "5.00 pm",
    "sold": "available",
    "condition": "used",
    "used": "1 year",
    "originalPrice": 1700000,
    "model": "Honda civic 409",
    "authenticity": "original",
    "features": "Touchscreen, Streaming and video gaming,Web browser,Easter eggs, Air suspension",
    "describetion": " The Honda City is smartly styled with dignified stature and superior technological prowess. A wide, upper-grill in the front presents the signature Honda Solid Wing Face, and elevates the car to a position of prominence"
  },

  {
    "categoryId": 3,
    "brand": "Toyota",

    "name": "Toyota",
    "price": "600000 ",
    "picture": "https://i.ibb.co/SrrmfvN/tesla.jpg",
    "location": "Dhaka mirpur- 2",
    "seller": "sayeed",
    "email": "sayeedh95@gmail.com",
    "verified": "true",
    "time": "4.00 pm",
    "sold": "available",
    "condition": "used",
    "used": "1 year",
    "originalPrice": 700000,
    "model": "Toyota Corolla",
    "authenticity": "original",
    "features": "Turning corners and heads,Modern, yet timeless.,Built for comfort and speed.",
    "describetion": "Toyota has car models that offer something for everyone. Whether you’re looking for a compact car for commuting to work, a fun sports car, or a family vehicle to safely transport your loved ones wherever they need to go, you can rely on Toyota. "
  },
  {
    "categoryId": 3,
    "brand": "Toyota",
    "name": "Toyota",
    "price": "600000 ",
    "picture": "https://i.ibb.co/SrrmfvN/tesla.jpg",
    "location": "Dhaka mirpur- 2",
    "seller": "sayeed",
    "email": "sayeedh95@gmail.com",
    "verified": "true",
    "time": "4.00 pm",
    "sold": "available",
    "condition": "used",
    "used": "1 year",
    "originalPrice": 700000,
    "model": "Toyota Corolla",
    "authenticity": "original",
    "features": "Turning corners and heads,Modern, yet timeless.,Built for comfort and speed.",
    "describetion": "Toyota has car models that offer something for everyone. Whether you’re looking for a compact car for commuting to work, a fun sports car, or a family vehicle to safely transport your loved ones wherever they need to go, you can rely on Toyota. "
  }
]


[
  {
    "categoryId": "1",
    "brand": "Tesla",
    "Logo": "https://www.logo.wine/a/logo/Tesla%2C_Inc./Tesla%2C_Inc.-Logomark%26Wordmark2-Dark-Background-Logo.wine.svg"
  },
  {
    "categoryId": "2",
    "brand": "Honda",
    "Logo": "https://wallpaperaccess.com/full/349467.jpg"
  },
  {
    "categoryId": "3",
    "brand": "Toyota",
    "Logo": "https://wallpapercave.com/wp/zmNqrb3.jpg"
  },
]